sspdata/__init__.py
sspdata/base/__init__.py
sspdata/base/crawler.py
sspdata/base/datasets.py
sspdata/base/requests.py
sspdata/datasets/__init__.py
sspdata/datasets/feminicidio.py
sspdata-0.0.2.dist-info/entry_points.txt
sspdata-0.0.2.dist-info/WHEEL
sspdata-0.0.2.dist-info/METADATA
sspdata-0.0.2.dist-info/RECORD
