Metadata-Version: 2.1
Name: sspdata
Version: 0.0.2
Summary: Aquisição de dados abertos de segurança pública do estado de São Paulo.
Author: Alexandre Farias
Author-email: 0800alefarias@gmail.com
Requires-Python: >=3.8,<4.0
Classifier: Programming Language :: Python :: 3
Classifier: Programming Language :: Python :: 3.8
Classifier: Programming Language :: Python :: 3.9
Requires-Dist: bs4 (>=0.0.1,<0.0.2)
Requires-Dist: pandas (>=1.2.3,<2.0.0)
Requires-Dist: requests (>=2.25.1,<3.0.0)
Requires-Dist: setuptools (>=57.0.0,<58.0.0)
